LICENSE
MANIFEST.in
README.md
pyproject.toml
setup.py
./dimos/__init__.py
./dimos/conftest.py
./dimos/constants.py
./dimos/agents/__init__.py
./dimos/agents/agent.py
./dimos/agents/conftest.py
./dimos/agents/ollama_agent.py
./dimos/agents/spec.py
./dimos/agents/system_prompt.py
./dimos/agents/test_agent.py
./dimos/agents/test_agent_direct.py
./dimos/agents/test_agent_fake.py
./dimos/agents/test_mock_agent.py
./dimos/agents/test_stash_agent.py
./dimos/agents/testing.py
./dimos/agents/cli/human.py
./dimos/agents/cli/web.py
./dimos/agents/skills/conftest.py
./dimos/agents/skills/demo_calculator_skill.py
./dimos/agents/skills/demo_google_maps_skill.py
./dimos/agents/skills/demo_gps_nav.py
./dimos/agents/skills/demo_robot.py
./dimos/agents/skills/demo_skill.py
./dimos/agents/skills/google_maps_skill_container.py
./dimos/agents/skills/gps_nav_skill.py
./dimos/agents/skills/navigation.py
./dimos/agents/skills/osm.py
./dimos/agents/skills/speak_skill.py
./dimos/agents/skills/test_google_maps_skill_container.py
./dimos/agents/skills/test_gps_nav_skills.py
./dimos/agents/skills/test_navigation.py
./dimos/agents/skills/test_unitree_skill_container.py
./dimos/agents/temp/webcam_agent.py
./dimos/agents_deprecated/__init__.py
./dimos/agents_deprecated/agent.py
./dimos/agents_deprecated/agent_config.py
./dimos/agents_deprecated/agent_message.py
./dimos/agents_deprecated/agent_types.py
./dimos/agents_deprecated/claude_agent.py
./dimos/agents_deprecated/memory/__init__.py
./dimos/agents_deprecated/memory/base.py
./dimos/agents_deprecated/memory/chroma_impl.py
./dimos/agents_deprecated/memory/image_embedding.py
./dimos/agents_deprecated/memory/spatial_vector_db.py
./dimos/agents_deprecated/memory/test_image_embedding.py
./dimos/agents_deprecated/memory/visual_memory.py
./dimos/agents_deprecated/modules/__init__.py
./dimos/agents_deprecated/modules/base.py
./dimos/agents_deprecated/modules/base_agent.py
./dimos/agents_deprecated/modules/gateway/__init__.py
osdimsterel.egg-info/PKG-INFO
osdimsterel.egg-info/SOURCES.txt
osdimsterel.egg-info/dependency_links.txt
osdimsterel.egg-info/entry_points.txt
osdimsterel.egg-info/requires.txt
osdimsterel.egg-info/top_level.txt