Metadata-Version: 2.4
Name: osdimsterel
Version: 0.0.6
Summary: Powering agentive generalist robotics
Author-email: Dimensional Team <build@dimensionalOS.com>
Requires-Python: >=3.10
License-File: LICENSE
Requires-Dist: opencv-python
Requires-Dist: numba>=0.60.0
Requires-Dist: llvmlite>=0.42.0
Requires-Dist: python-dotenv
Requires-Dist: openai
Requires-Dist: anthropic>=0.19.0
Requires-Dist: cerebras-cloud-sdk
Requires-Dist: moondream
Requires-Dist: numpy>=1.26.4
Requires-Dist: colorlog==6.9.0
Requires-Dist: yapf==0.40.2
Requires-Dist: typeguard
Requires-Dist: empy==3.3.4
Requires-Dist: catkin_pkg
Requires-Dist: lark
Requires-Dist: plum-dispatch==2.5.7
Requires-Dist: ffmpeg-python
Requires-Dist: tiktoken>=0.8.0
Requires-Dist: Flask>=2.2
Requires-Dist: python-multipart==0.0.20
Requires-Dist: reactivex
Requires-Dist: asyncio==3.4.3
Requires-Dist: unitree-webrtc-connect-leshy>=2.0.7
Requires-Dist: tensorzero==2025.7.5
Requires-Dist: structlog<26,>=25.5.0
Requires-Dist: fastapi>=0.115.6
Requires-Dist: sse-starlette>=2.2.1
Requires-Dist: uvicorn>=0.34.0
Requires-Dist: langchain<2,>=1
Requires-Dist: langchain-chroma<2,>=1
Requires-Dist: langchain-core<2,>=1
Requires-Dist: langchain-openai<2,>=1
Requires-Dist: langchain-text-splitters<2,>=1
Requires-Dist: langchain-huggingface<2,>=1
Requires-Dist: langchain-ollama<2,>=1
Requires-Dist: bitsandbytes<1.0,>=0.48.2; sys_platform == "linux"
Requires-Dist: ollama>=0.6.0
Requires-Dist: pydantic
Requires-Dist: ipykernel
Requires-Dist: pycryptodome
Requires-Dist: sounddevice
Requires-Dist: pyaudio
Requires-Dist: requests
Requires-Dist: wasmtime
Requires-Dist: PyTurboJPEG==1.8.2
Requires-Dist: openai-whisper
Requires-Dist: soundfile
Requires-Dist: transformers[torch]==4.49.0
Requires-Dist: sentence_transformers
Requires-Dist: ultralytics>=8.3.70
Requires-Dist: filterpy>=1.4.5
Requires-Dist: scipy>=1.15.1
Requires-Dist: scikit-learn
Requires-Dist: Pillow
Requires-Dist: clip
Requires-Dist: timm>=1.0.15
Requires-Dist: lap>=0.5.12
Requires-Dist: opencv-contrib-python==4.10.0.84
Requires-Dist: open_clip_torch==3.2.0
Requires-Dist: torchreid==0.2.5
Requires-Dist: gdown==5.2.0
Requires-Dist: tensorboard==2.20.0
Requires-Dist: open3d
Requires-Dist: googlemaps>=4.10.0
Requires-Dist: onnx
Requires-Dist: einops==0.8.1
Requires-Dist: dask[complete]==2025.5.1
Requires-Dist: dimos-lcm
Requires-Dist: pydantic-settings<3,>=2.11.0
Requires-Dist: typer<1,>=0.19.2
Requires-Dist: plotext==5.3.2
Requires-Dist: pygame>=2.6.1
Requires-Dist: xarm-python-sdk>=1.17.0
Requires-Dist: numba>=0.60.0
Requires-Dist: llvmlite>=0.42.0
Provides-Extra: manipulation
Requires-Dist: h5py>=3.7.0; extra == "manipulation"
Requires-Dist: pyrender>=0.1.45; extra == "manipulation"
Requires-Dist: trimesh>=3.22.0; extra == "manipulation"
Requires-Dist: python-fcl>=0.7.0.4; extra == "manipulation"
Requires-Dist: pyquaternion>=0.9.9; extra == "manipulation"
Requires-Dist: matplotlib>=3.7.1; extra == "manipulation"
Requires-Dist: rtree; extra == "manipulation"
Requires-Dist: pandas>=1.5.2; extra == "manipulation"
Requires-Dist: tqdm>=4.65.0; extra == "manipulation"
Requires-Dist: pyyaml>=6.0; extra == "manipulation"
Requires-Dist: contact-graspnet-pytorch; extra == "manipulation"
Requires-Dist: piper-sdk; extra == "manipulation"
Requires-Dist: kaleido>=0.2.1; extra == "manipulation"
Requires-Dist: plotly>=5.9.0; extra == "manipulation"
Provides-Extra: cpu
Requires-Dist: onnxruntime; extra == "cpu"
Requires-Dist: ctransformers==0.2.27; extra == "cpu"
Provides-Extra: cuda
Requires-Dist: cupy-cuda12x==13.6.0; extra == "cuda"
Requires-Dist: nvidia-nvimgcodec-cu12[all]; extra == "cuda"
Requires-Dist: onnxruntime-gpu>=1.17.1; extra == "cuda"
Requires-Dist: ctransformers[cuda]==0.2.27; extra == "cuda"
Requires-Dist: mmengine>=0.10.3; extra == "cuda"
Requires-Dist: mmcv>=2.1.0; extra == "cuda"
Requires-Dist: xformers>=0.0.20; extra == "cuda"
Requires-Dist: mss; extra == "cuda"
Requires-Dist: dataclasses; extra == "cuda"
Requires-Dist: ftfy; extra == "cuda"
Requires-Dist: regex; extra == "cuda"
Requires-Dist: fasttext; extra == "cuda"
Requires-Dist: lvis; extra == "cuda"
Requires-Dist: nltk; extra == "cuda"
Requires-Dist: clip; extra == "cuda"
Requires-Dist: detectron2; extra == "cuda"
Provides-Extra: dev
Requires-Dist: ruff==0.14.3; extra == "dev"
Requires-Dist: mypy==1.19.0; extra == "dev"
Requires-Dist: pre_commit==4.2.0; extra == "dev"
Requires-Dist: pytest==8.3.5; extra == "dev"
Requires-Dist: pytest-asyncio==0.26.0; extra == "dev"
Requires-Dist: pytest-mock==3.15.0; extra == "dev"
Requires-Dist: pytest-env==1.1.5; extra == "dev"
Requires-Dist: pytest-timeout==2.4.0; extra == "dev"
Requires-Dist: coverage>=7.0; extra == "dev"
Requires-Dist: textual==3.7.1; extra == "dev"
Requires-Dist: requests-mock==1.12.1; extra == "dev"
Requires-Dist: terminaltexteffects==0.12.2; extra == "dev"
Requires-Dist: lxml-stubs<1,>=0.5.1; extra == "dev"
Requires-Dist: pandas-stubs<3,>=2.3.2.250926; extra == "dev"
Requires-Dist: types-PySocks<2,>=1.7.1.20251001; extra == "dev"
Requires-Dist: types-PyYAML<7,>=6.0.12.20250915; extra == "dev"
Requires-Dist: types-colorama<1,>=0.4.15.20250801; extra == "dev"
Requires-Dist: types-defusedxml<1,>=0.7.0.20250822; extra == "dev"
Requires-Dist: types-gevent<26,>=25.4.0.20250915; extra == "dev"
Requires-Dist: types-greenlet<4,>=3.2.0.20250915; extra == "dev"
Requires-Dist: types-jmespath<2,>=1.0.2.20250809; extra == "dev"
Requires-Dist: types-jsonschema<5,>=4.25.1.20251009; extra == "dev"
Requires-Dist: types-networkx<4,>=3.5.0.20251001; extra == "dev"
Requires-Dist: types-protobuf<7,>=6.32.1.20250918; extra == "dev"
Requires-Dist: types-psutil<8,>=7.0.0.20251001; extra == "dev"
Requires-Dist: types-pytz<2026,>=2025.2.0.20250809; extra == "dev"
Requires-Dist: types-simplejson<4,>=3.20.0.20250822; extra == "dev"
Requires-Dist: types-tabulate<1,>=0.9.0.20241207; extra == "dev"
Requires-Dist: types-tensorflow<3,>=2.18.0.20251008; extra == "dev"
Requires-Dist: types-tqdm<5,>=4.67.0.20250809; extra == "dev"
Provides-Extra: sim
Requires-Dist: mujoco>=3.3.4; extra == "sim"
Requires-Dist: playground>=0.0.5; extra == "sim"
Provides-Extra: drone
Requires-Dist: pymavlink; extra == "drone"
Dynamic: license-file
